kaldi_helpers/__init__.py
kaldi_helpers/inference_scripts/__init__.py
kaldi_helpers/input_scripts/__init__.py
kaldi_helpers/input_scripts/clean_json.py
kaldi_helpers/input_scripts/elan_to_json.py
kaldi_helpers/input_scripts/json_to_kaldi.py
kaldi_helpers/input_scripts/make_prn_dict.py
kaldi_helpers/input_scripts/make_wordlist.py
kaldi_helpers/input_scripts/resample_audio.py
kaldi_helpers/input_scripts/split_on_silence.py
kaldi_helpers/input_scripts/textgrid_to_json.py
kaldi_helpers/input_scripts/trs_to_json.py
kaldi_helpers/output_scripts/__init__.py
kaldi_helpers/output_scripts/ctm_to_textgrid.py
kaldi_helpers/output_scripts/textgrid_to_elan.py
kaldi_helpers/script_utilities/__init__.py
kaldi_helpers/script_utilities/file_utilities.py
kaldi_helpers/script_utilities/globals.py
kaldi_helpers/script_utilities/json_utilities.py
test/__init__.py
test/test.py
test/test_clean_json.py
test/test_elan_to_json.py
test/test_json_to_kaldi.py
test/test_make_prn_dict.py
test/test_make_wordlist.py
test/test_resample_audio.py
test/test_silence_audio.py
test/test_split_eafs.py
test/test_textgrid_to_json.py
test/test_trs_to_json.py
test/test_utilities.py
test/output_tests/__init__.py
test/output_tests/test_ctm_to_textgrid.py
test/output_tests/test_textgrid_to_elan.py
kaldi_helpers-0.22.dist-info/METADATA
kaldi_helpers-0.22.dist-info/WHEEL
kaldi_helpers-0.22.dist-info/top_level.txt
kaldi_helpers-0.22.dist-info/RECORD
