Metadata-Version: 2.1
Name: kaldi-helpers
Version: 0.22
Summary: Scripts for preparing language data for use with Kaldi ASR
Home-page: https://github.com/CoEDL/kaldi_helpers
Author: CoEDL
Author-email: n.lambourne@uq.edu.au
License: UNKNOWN
Platform: UNKNOWN
Classifier: Programming Language :: Python :: 3.6
Classifier: Topic :: Text Processing :: Linguistic
Classifier: Operating System :: OS Independent
Requires-Dist: pytest
Requires-Dist: pympi-ling
Requires-Dist: numpy
Requires-Dist: langid
Requires-Dist: nltk
Requires-Dist: praatio
Requires-Dist: pydub
